botw_duplicator_tools/__init__.py
botw_duplicator_tools/__main__.py
botw_duplicator_tools/actorinfo_tool.py
botw_duplicator_tools/actorpack_tool.py
botw_duplicator_tools/bfres_duplicator.py
botw_duplicator_tools-1.7.dist-info/METADATA
botw_duplicator_tools-1.7.dist-info/RECORD
botw_duplicator_tools-1.7.dist-info/WHEEL
botw_duplicator_tools-1.7.dist-info/entry_points.txt
botw_duplicator_tools-1.7.dist-info/top_level.txt
