Metadata-Version: 2.1
Name: botw-duplicator-tools
Version: 1.7
Summary: Tools for duplicating actors and models, for modding the game 'The Legend of Zelda: Breath of the Wild'.
Home-page: http://github.com/BravelyPeculiar/botw_duplicator_tools
Author: BravelyPeculiar
Author-email: joshuawaltonm@gmail.com
License: MIT
Download-URL: https://github.com/BravelyPeculiar/botw_duplicator_tools/archive/1.0.tar.gz
Platform: UNKNOWN
Classifier: Programming Language :: Python :: 3
Classifier: License :: OSI Approved :: MIT License
Classifier: Operating System :: OS Independent
Requires-Python: >=3.6
Requires-Dist: wszst-yaz0 (>=1.0)
Requires-Dist: byml (>=1.0)
Requires-Dist: sarc (>=1.0)
Requires-Dist: aamp (>=1.0)
